{
    "libosinfo": {
        "-version": "0.0.1",
        "os": {
            "short-id": "cirros0.4.0",
            "_name": "CirrOS 0.4.0",
            "_vendor": "CirrOS",
            "upgrades": {
                "-id": "http://cirros-cloud.net/cirros/0.3.5"
            },
            "devices": {
                "device": [
                    {
                        "-id": "http://pcisig.com/pci/1af4/1041"
                    },
                    {
                        "-id": "http://pcisig.com/pci/1af4/1042"
                    },
                    {
                        "-id": "http://pcisig.com/pci/1af4/1043"
                    },
                    {
                        "-id": "http://pcisig.com/pci/1af4/1044"
                    },
                    {
                        "-id": "http://pcisig.com/pci/1af4/1045"
                    },
                    {
                        "-id": "http://pcisig.com/pci/1af4/1048"
                    },
                    {
                        "-id": "http://pcisig.com/pci/1af4/1049"
                    },
                    {
                        "-id": "http://pcisig.com/pci/1af4/1052"
                    }
                ]
            },
            "resources": {
                "-arch": "all",
                "minimum": {
                    "ram": "134217728",
                    "storage": "52428800",
                    "cpu": "1000000000",
                    "n-cpus": "1"
                }
            },
            "-id": "http://cirros-cloud.net/cirros/0.4.0",
            "version": "0.4.0",
            "family": "linux",
            "distro": "cirros",
            "derives-from": {
                "-id": "http://cirros-cloud.net/cirros/0.3.5"
            },
            "release-date": "2017-11-20"
        }
    }
}
